{
  "trade_date": "2025-12-18",
  "generated_time": "2025-12-18T11:23:57.543851",
  "selector_alias": "B1战法",
  "total_stocks": 11,
  "selected_stocks": [
    "605086",
    "002371",
    "000333",
    "603931",
    "002166",
    "002117",
    "002301",
    "603355",
    "603408",
    "002898",
    "002235"
  ],
  "stock_details": {
    "605086": {
      "name": "龙高股份",
      "industry": "B10非金属矿采选业",
      "market": "上海",
      "close_price": 38.27,
      "market_cap": 57405000000.00001,
      "pe_ttm": 61.424116,
      "pb_mrq": 5.364766,
      "latest_close": 38.27,
      "latest_volume": 24165.0,
      "latest_date": "2025-12-18"
    },
    "002371": {
      "name": "北方华创",
      "industry": "C35专用设备制造业",
      "market": "深圳",
      "close_price": 443.1,
      "market_cap": 354480000000.0,
      "pe_ttm": 51.086608,
      "pb_mrq": 8.90658,
      "latest_close": 443.1,
      "latest_volume": 41921.0,
      "latest_date": "2025-12-18"
    },
    "000333": {
      "name": "美的集团",
      "industry": "C38电气机械和器材制造业",
      "market": "深圳",
      "close_price": 79.83,
      "market_cap": 63864000000.0,
      "pe_ttm": 13.729149,
      "pb_mrq": 2.783779,
      "latest_close": 79.83,
      "latest_volume": 214097.0,
      "latest_date": "2025-12-18"
    },
    "603931": {
      "name": "格林达",
      "industry": "C26化学原料和化学制品制造业",
      "market": "上海",
      "close_price": 32.99,
      "market_cap": 49485000000.0,
      "pe_ttm": 51.592551,
      "pb_mrq": 4.080519,
      "latest_close": 32.99,
      "latest_volume": 68104.0,
      "latest_date": "2025-12-18"
    },
    "002166": {
      "name": "莱茵生物",
      "industry": "C27医药制造业",
      "market": "深圳",
      "close_price": 8.7,
      "market_cap": 6959999999.999999,
      "pe_ttm": 48.959542,
      "pb_mrq": 2.097156,
      "latest_close": 8.7,
      "latest_volume": 5.877471754111438e-39,
      "latest_date": "2025-12-18"
    },
    "002117": {
      "name": "东港股份",
      "industry": "C23印刷和记录媒介复制业",
      "market": "深圳",
      "close_price": 12.82,
      "market_cap": 10256000000.0,
      "pe_ttm": 33.450469,
      "pb_mrq": 4.75877,
      "latest_close": 12.82,
      "latest_volume": 144217.0,
      "latest_date": "2025-12-18"
    },
    "002301": {
      "name": "齐心集团",
      "industry": "C24文教、工美、体育和娱乐用品制造业",
      "market": "深圳",
      "close_price": 7.4,
      "market_cap": 5920000000.0,
      "pe_ttm": 119.516912,
      "pb_mrq": 1.69978,
      "latest_close": 7.4,
      "latest_volume": 267653.0,
      "latest_date": "2025-12-18"
    },
    "603355": {
      "name": "莱克电气",
      "industry": "C38电气机械和器材制造业",
      "market": "上海",
      "close_price": 30.43,
      "market_cap": 45645000000.0,
      "pe_ttm": 17.936134,
      "pb_mrq": 3.193654,
      "latest_close": 30.43,
      "latest_volume": 80965.0,
      "latest_date": "2025-12-18"
    },
    "603408": {
      "name": "建霖家居",
      "industry": "C29橡胶和塑料制品业",
      "market": "上海",
      "close_price": 12.85,
      "market_cap": 19275000000.0,
      "pe_ttm": 13.256676,
      "pb_mrq": 1.675608,
      "latest_close": 12.85,
      "latest_volume": 84645.0,
      "latest_date": "2025-12-18"
    },
    "002898": {
      "name": "*ST赛隆",
      "industry": "C27医药制造业",
      "market": "深圳",
      "close_price": 13.9,
      "market_cap": 11120000000.0,
      "pe_ttm": -35.023249,
      "pb_mrq": 5.312782,
      "latest_close": 13.9,
      "latest_volume": 5552.0,
      "latest_date": "2025-12-18"
    },
    "002235": {
      "name": "安妮股份",
      "industry": "C22造纸和纸制品业",
      "market": "深圳",
      "close_price": 10.5,
      "market_cap": 8400000000.0,
      "pe_ttm": 2925.013189,
      "pb_mrq": 8.097222,
      "latest_close": 10.5,
      "latest_volume": 1237048.0,
      "latest_date": "2025-12-18"
    }
  }
}