{
  "trade_date": "2025-12-19",
  "generated_time": "2025-12-19T11:29:12.515890",
  "selector_alias": "填坑战法",
  "total_stocks": 3,
  "selected_stocks": [
    "603650",
    "002725",
    "603681"
  ],
  "stock_details": {
    "603650": {
      "name": "彤程新材",
      "industry": "C26化学原料和化学制品制造业",
      "market": "上海",
      "close_price": 44.68,
      "market_cap": 67020000000.0,
      "pe_ttm": 48.102759,
      "pb_mrq": 8.019687,
      "latest_close": 44.68,
      "latest_volume": 192466.0,
      "latest_date": "2025-12-19"
    },
    "002725": {
      "name": "跃岭股份",
      "industry": "C36汽车制造业",
      "market": "深圳",
      "close_price": 17.13,
      "market_cap": 13704000000.0,
      "pe_ttm": 59.789695,
      "pb_mrq": 4.256859,
      "latest_close": 17.13,
      "latest_volume": 241374.0,
      "latest_date": "2025-12-19"
    },
    "603681": {
      "name": "永冠新材",
      "industry": "C26化学原料和化学制品制造业",
      "market": "上海",
      "close_price": 18.15,
      "market_cap": 27224999999.999996,
      "pe_ttm": 23.459784,
      "pb_mrq": 1.332906,
      "latest_close": 18.15,
      "latest_volume": 37220.0,
      "latest_date": "2025-12-19"
    }
  }
}