{
  "trade_date": "2025-10-15",
  "generated_time": "2025-10-15T11:29:31.524266",
  "selector_alias": "上穿60放量战法",
  "total_stocks": 5,
  "selected_stocks": [
    "603324",
    "002295",
    "603285",
    "603790",
    "002453"
  ],
  "stock_details": {
    "603324": {
      "name": "盛剑科技",
      "industry": "C35专用设备制造业",
      "market": "上海",
      "close_price": 27.24,
      "market_cap": 40860000000.0,
      "pe_ttm": 41.97475,
      "pb_mrq": 2.375367,
      "latest_close": 27.24,
      "latest_volume": 21360.0,
      "latest_date": "2025-10-15"
    },
    "002295": {
      "name": "精艺股份",
      "industry": "C32有色金属冶炼和压延加工业",
      "market": "深圳",
      "close_price": 13.2,
      "market_cap": 10560000000.0,
      "pe_ttm": 169.383312,
      "pb_mrq": 2.447229,
      "latest_close": 13.2,
      "latest_volume": 275818.0,
      "latest_date": "2025-10-15"
    },
    "603285": {
      "name": "键邦股份",
      "industry": "C26化学原料和化学制品制造业",
      "market": "上海",
      "close_price": 26.37,
      "market_cap": 39555000000.0,
      "pe_ttm": 32.219171,
      "pb_mrq": 2.573179,
      "latest_close": 26.37,
      "latest_volume": 29082.0,
      "latest_date": "2025-10-15"
    },
    "603790": {
      "name": "雅运股份",
      "industry": "C26化学原料和化学制品制造业",
      "market": "上海",
      "close_price": 21.47,
      "market_cap": 32205000000.0,
      "pe_ttm": 70.001819,
      "pb_mrq": 3.327022,
      "latest_close": 21.47,
      "latest_volume": 21339.0,
      "latest_date": "2025-10-15"
    },
    "002453": {
      "name": "华软科技",
      "industry": "C26化学原料和化学制品制造业",
      "market": "深圳",
      "close_price": 6.95,
      "market_cap": 5560000000.0,
      "pe_ttm": -17.675178,
      "pb_mrq": 5.94247,
      "latest_close": 6.95,
      "latest_volume": 621221.0,
      "latest_date": "2025-10-15"
    }
  }
}